<?xml version="1.0" encoding="iso-8859-1"?>
<AnalysisHistory filename="C:\Users\John\Documents\Visual Studio 2015\Projects\Cryptography\CEX++\CEX\HCR.cpp"><Results tool="PC-lint"><Result Date="2018-01-06T18:08:35"><Categories issues="183"><Category id="0" name="Elective Note" issues="2"/><Category id="1" name="Information" issues="22"/><Category id="2" name="Warning" issues="39"/><Category id="3" name="Error" issues="116"/><Category id="4" name="Internal Error" issues="4"/><Category id="5" name="Fatal Error" issues="0"/></Categories><Issues><Issue id="10" category="3" count="19"/><Issue id="1016" category="3" count="1"/><Issue id="1049" category="3" count="3"/><Issue id="1062" category="3" count="36"/><Issue id="1113" category="3" count="1"/><Issue id="1220" category="4" count="4"/><Issue id="151" category="3" count="1"/><Issue id="1960" category="0" count="1"/><Issue id="36" category="3" count="10"/><Issue id="39" category="3" count="10"/><Issue id="40" category="3" count="9"/><Issue id="537" category="2" count="38"/><Issue id="55" category="3" count="2"/><Issue id="602" category="2" count="1"/><Issue id="78" category="3" count="19"/><Issue id="830" category="1" count="22"/><Issue id="96" category="3" count="1"/><Issue id="974" category="0" count="1"/><Issue id="98" category="3" count="4"/></Issues></Result><Result Date="2018-01-19T13:04:42"><Categories issues="181"><Category id="0" name="Elective Note" issues="1"/><Category id="1" name="Information" issues="22"/><Category id="2" name="Warning" issues="38"/><Category id="3" name="Error" issues="116"/><Category id="4" name="Internal Error" issues="4"/><Category id="5" name="Fatal Error" issues="0"/></Categories><Issues><Issue id="10" category="3" count="19"/><Issue id="1016" category="3" count="1"/><Issue id="1049" category="3" count="3"/><Issue id="1062" category="3" count="36"/><Issue id="1113" category="3" count="1"/><Issue id="1220" category="4" count="4"/><Issue id="151" category="3" count="1"/><Issue id="36" category="3" count="10"/><Issue id="39" category="3" count="10"/><Issue id="40" category="3" count="9"/><Issue id="537" category="2" count="38"/><Issue id="55" category="3" count="2"/><Issue id="78" category="3" count="19"/><Issue id="830" category="1" count="22"/><Issue id="96" category="3" count="1"/><Issue id="974" category="0" count="1"/><Issue id="98" category="3" count="4"/></Issues></Result><Result Date="2018-01-19T13:33:16"><Categories issues="182"><Category id="0" name="Elective Note" issues="1"/><Category id="1" name="Information" issues="22"/><Category id="2" name="Warning" issues="39"/><Category id="3" name="Error" issues="116"/><Category id="4" name="Internal Error" issues="4"/><Category id="5" name="Fatal Error" issues="0"/></Categories><Issues><Issue id="10" category="3" count="19"/><Issue id="1016" category="3" count="1"/><Issue id="1049" category="3" count="3"/><Issue id="1062" category="3" count="36"/><Issue id="1113" category="3" count="1"/><Issue id="1220" category="4" count="4"/><Issue id="151" category="3" count="1"/><Issue id="36" category="3" count="10"/><Issue id="39" category="3" count="10"/><Issue id="40" category="3" count="9"/><Issue id="537" category="2" count="38"/><Issue id="55" category="3" count="2"/><Issue id="686" category="2" count="1"/><Issue id="78" category="3" count="19"/><Issue id="830" category="1" count="22"/><Issue id="96" category="3" count="1"/><Issue id="974" category="0" count="1"/><Issue id="98" category="3" count="4"/></Issues></Result><Result Date="2018-01-19T13:35:41"><Categories issues="349"><Category id="0" name="Elective Note" issues="1"/><Category id="1" name="Information" issues="36"/><Category id="2" name="Warning" issues="192"/><Category id="3" name="Error" issues="116"/><Category id="4" name="Internal Error" issues="4"/><Category id="5" name="Fatal Error" issues="0"/></Categories><Issues><Issue id="10" category="3" count="19"/><Issue id="1016" category="3" count="1"/><Issue id="1049" category="3" count="3"/><Issue id="1062" category="3" count="36"/><Issue id="1113" category="3" count="1"/><Issue id="1220" category="4" count="4"/><Issue id="1505" category="2" count="115"/><Issue id="151" category="3" count="1"/><Issue id="1573" category="2" count="7"/><Issue id="36" category="3" count="10"/><Issue id="39" category="3" count="10"/><Issue id="40" category="3" count="9"/><Issue id="431" category="2" count="7"/><Issue id="451" category="2" count="3"/><Issue id="503" category="2" count="2"/><Issue id="515" category="2" count="3"/><Issue id="530" category="2" count="6"/><Issue id="537" category="2" count="41"/><Issue id="55" category="3" count="2"/><Issue id="553" category="2" count="4"/><Issue id="631" category="2" count="4"/><Issue id="78" category="3" count="19"/><Issue id="830" category="1" count="36"/><Issue id="96" category="3" count="1"/><Issue id="974" category="0" count="1"/><Issue id="98" category="3" count="4"/></Issues></Result><Result Date="2018-01-19T13:39:45"><Categories issues="349"><Category id="0" name="Elective Note" issues="1"/><Category id="1" name="Information" issues="36"/><Category id="2" name="Warning" issues="192"/><Category id="3" name="Error" issues="116"/><Category id="4" name="Internal Error" issues="4"/><Category id="5" name="Fatal Error" issues="0"/></Categories><Issues><Issue id="10" category="3" count="19"/><Issue id="1016" category="3" count="1"/><Issue id="1049" category="3" count="3"/><Issue id="1062" category="3" count="36"/><Issue id="1113" category="3" count="1"/><Issue id="1220" category="4" count="4"/><Issue id="1505" category="2" count="115"/><Issue id="151" category="3" count="1"/><Issue id="1573" category="2" count="7"/><Issue id="36" category="3" count="10"/><Issue id="39" category="3" count="10"/><Issue id="40" category="3" count="9"/><Issue id="431" category="2" count="7"/><Issue id="451" category="2" count="3"/><Issue id="503" category="2" count="2"/><Issue id="515" category="2" count="3"/><Issue id="530" category="2" count="6"/><Issue id="537" category="2" count="41"/><Issue id="55" category="3" count="2"/><Issue id="553" category="2" count="4"/><Issue id="631" category="2" count="4"/><Issue id="78" category="3" count="19"/><Issue id="830" category="1" count="36"/><Issue id="96" category="3" count="1"/><Issue id="974" category="0" count="1"/><Issue id="98" category="3" count="4"/></Issues></Result><Result Date="2018-01-19T14:04:39"><Categories issues="350"><Category id="0" name="Elective Note" issues="1"/><Category id="1" name="Information" issues="36"/><Category id="2" name="Warning" issues="193"/><Category id="3" name="Error" issues="116"/><Category id="4" name="Internal Error" issues="4"/><Category id="5" name="Fatal Error" issues="0"/></Categories><Issues><Issue id="10" category="3" count="19"/><Issue id="1016" category="3" count="1"/><Issue id="1049" category="3" count="3"/><Issue id="1062" category="3" count="36"/><Issue id="1113" category="3" count="1"/><Issue id="1220" category="4" count="4"/><Issue id="1505" category="2" count="115"/><Issue id="151" category="3" count="1"/><Issue id="1573" category="2" count="7"/><Issue id="36" category="3" count="10"/><Issue id="39" category="3" count="10"/><Issue id="40" category="3" count="9"/><Issue id="431" category="2" count="7"/><Issue id="451" category="2" count="3"/><Issue id="503" category="2" count="2"/><Issue id="515" category="2" count="3"/><Issue id="530" category="2" count="6"/><Issue id="537" category="2" count="41"/><Issue id="55" category="3" count="2"/><Issue id="553" category="2" count="4"/><Issue id="631" category="2" count="4"/><Issue id="686" category="2" count="1"/><Issue id="78" category="3" count="19"/><Issue id="830" category="1" count="36"/><Issue id="96" category="3" count="1"/><Issue id="974" category="0" count="1"/><Issue id="98" category="3" count="4"/></Issues></Result><Result Date="2018-01-19T14:05:44"><Categories issues="350"><Category id="0" name="Elective Note" issues="1"/><Category id="1" name="Information" issues="36"/><Category id="2" name="Warning" issues="193"/><Category id="3" name="Error" issues="116"/><Category id="4" name="Internal Error" issues="4"/><Category id="5" name="Fatal Error" issues="0"/></Categories><Issues><Issue id="10" category="3" count="19"/><Issue id="1016" category="3" count="1"/><Issue id="1049" category="3" count="3"/><Issue id="1062" category="3" count="36"/><Issue id="1113" category="3" count="1"/><Issue id="1220" category="4" count="4"/><Issue id="1505" category="2" count="115"/><Issue id="151" category="3" count="1"/><Issue id="1573" category="2" count="7"/><Issue id="36" category="3" count="10"/><Issue id="39" category="3" count="10"/><Issue id="40" category="3" count="9"/><Issue id="431" category="2" count="7"/><Issue id="451" category="2" count="3"/><Issue id="503" category="2" count="2"/><Issue id="515" category="2" count="3"/><Issue id="530" category="2" count="6"/><Issue id="537" category="2" count="41"/><Issue id="55" category="3" count="2"/><Issue id="553" category="2" count="4"/><Issue id="631" category="2" count="4"/><Issue id="686" category="2" count="1"/><Issue id="78" category="3" count="19"/><Issue id="830" category="1" count="36"/><Issue id="96" category="3" count="1"/><Issue id="974" category="0" count="1"/><Issue id="98" category="3" count="4"/></Issues></Result><Result Date="2018-01-19T14:07:52"><Categories issues="182"><Category id="0" name="Elective Note" issues="1"/><Category id="1" name="Information" issues="22"/><Category id="2" name="Warning" issues="39"/><Category id="3" name="Error" issues="116"/><Category id="4" name="Internal Error" issues="4"/><Category id="5" name="Fatal Error" issues="0"/></Categories><Issues><Issue id="10" category="3" count="19"/><Issue id="1016" category="3" count="1"/><Issue id="1049" category="3" count="3"/><Issue id="1062" category="3" count="36"/><Issue id="1113" category="3" count="1"/><Issue id="1220" category="4" count="4"/><Issue id="151" category="3" count="1"/><Issue id="36" category="3" count="10"/><Issue id="39" category="3" count="10"/><Issue id="40" category="3" count="9"/><Issue id="537" category="2" count="38"/><Issue id="55" category="3" count="2"/><Issue id="686" category="2" count="1"/><Issue id="78" category="3" count="19"/><Issue id="830" category="1" count="22"/><Issue id="96" category="3" count="1"/><Issue id="974" category="0" count="1"/><Issue id="98" category="3" count="4"/></Issues></Result><Result Date="2018-01-19T14:08:53"><Categories issues="46"><Category id="0" name="Elective Note" issues="1"/><Category id="1" name="Information" issues="0"/><Category id="2" name="Warning" issues="39"/><Category id="3" name="Error" issues="2"/><Category id="4" name="Internal Error" issues="4"/><Category id="5" name="Fatal Error" issues="0"/></Categories><Issues><Issue id="10" category="3" count="1"/><Issue id="1220" category="4" count="4"/><Issue id="537" category="2" count="38"/><Issue id="686" category="2" count="1"/><Issue id="96" category="3" count="1"/><Issue id="974" category="0" count="1"/></Issues></Result><Result Date="2018-01-19T14:39:04"><Categories issues="42"><Category id="0" name="Elective Note" issues="1"/><Category id="1" name="Information" issues="0"/><Category id="2" name="Warning" issues="39"/><Category id="3" name="Error" issues="2"/><Category id="4" name="Internal Error" issues="0"/><Category id="5" name="Fatal Error" issues="0"/></Categories><Issues><Issue id="10" category="3" count="1"/><Issue id="537" category="2" count="38"/><Issue id="686" category="2" count="1"/><Issue id="96" category="3" count="1"/><Issue id="974" category="0" count="1"/></Issues></Result><Result Date="2018-01-19T14:41:52"><Categories issues="42"><Category id="0" name="Elective Note" issues="1"/><Category id="1" name="Information" issues="0"/><Category id="2" name="Warning" issues="39"/><Category id="3" name="Error" issues="2"/><Category id="4" name="Internal Error" issues="0"/><Category id="5" name="Fatal Error" issues="0"/></Categories><Issues><Issue id="10" category="3" count="1"/><Issue id="537" category="2" count="38"/><Issue id="686" category="2" count="1"/><Issue id="96" category="3" count="1"/><Issue id="974" category="0" count="1"/></Issues></Result><Result Date="2018-01-19T15:10:55"><Categories issues="181"><Category id="0" name="Elective Note" issues="1"/><Category id="1" name="Information" issues="22"/><Category id="2" name="Warning" issues="38"/><Category id="3" name="Error" issues="116"/><Category id="4" name="Internal Error" issues="4"/><Category id="5" name="Fatal Error" issues="0"/></Categories><Issues><Issue id="10" category="3" count="19"/><Issue id="1016" category="3" count="1"/><Issue id="1049" category="3" count="3"/><Issue id="1062" category="3" count="36"/><Issue id="1113" category="3" count="1"/><Issue id="1220" category="4" count="4"/><Issue id="151" category="3" count="1"/><Issue id="36" category="3" count="10"/><Issue id="39" category="3" count="10"/><Issue id="40" category="3" count="9"/><Issue id="537" category="2" count="38"/><Issue id="55" category="3" count="2"/><Issue id="78" category="3" count="19"/><Issue id="830" category="1" count="22"/><Issue id="96" category="3" count="1"/><Issue id="974" category="0" count="1"/><Issue id="98" category="3" count="4"/></Issues></Result><Result Date="2018-01-19T15:16:31"><Categories issues="181"><Category id="0" name="Elective Note" issues="1"/><Category id="1" name="Information" issues="22"/><Category id="2" name="Warning" issues="38"/><Category id="3" name="Error" issues="116"/><Category id="4" name="Internal Error" issues="4"/><Category id="5" name="Fatal Error" issues="0"/></Categories><Issues><Issue id="10" category="3" count="19"/><Issue id="1016" category="3" count="1"/><Issue id="1049" category="3" count="3"/><Issue id="1062" category="3" count="36"/><Issue id="1113" category="3" count="1"/><Issue id="1220" category="4" count="4"/><Issue id="151" category="3" count="1"/><Issue id="36" category="3" count="10"/><Issue id="39" category="3" count="10"/><Issue id="40" category="3" count="9"/><Issue id="537" category="2" count="38"/><Issue id="55" category="3" count="2"/><Issue id="78" category="3" count="19"/><Issue id="830" category="1" count="22"/><Issue id="96" category="3" count="1"/><Issue id="974" category="0" count="1"/><Issue id="98" category="3" count="4"/></Issues></Result><Result Date="2018-01-19T15:17:07"><Categories issues="181"><Category id="0" name="Elective Note" issues="1"/><Category id="1" name="Information" issues="22"/><Category id="2" name="Warning" issues="38"/><Category id="3" name="Error" issues="116"/><Category id="4" name="Internal Error" issues="4"/><Category id="5" name="Fatal Error" issues="0"/></Categories><Issues><Issue id="10" category="3" count="19"/><Issue id="1016" category="3" count="1"/><Issue id="1049" category="3" count="3"/><Issue id="1062" category="3" count="36"/><Issue id="1113" category="3" count="1"/><Issue id="1220" category="4" count="4"/><Issue id="151" category="3" count="1"/><Issue id="36" category="3" count="10"/><Issue id="39" category="3" count="10"/><Issue id="40" category="3" count="9"/><Issue id="537" category="2" count="38"/><Issue id="55" category="3" count="2"/><Issue id="78" category="3" count="19"/><Issue id="830" category="1" count="22"/><Issue id="96" category="3" count="1"/><Issue id="974" category="0" count="1"/><Issue id="98" category="3" count="4"/></Issues></Result><Result Date="2018-01-19T15:29:30"><Categories issues="182"><Category id="0" name="Elective Note" issues="1"/><Category id="1" name="Information" issues="22"/><Category id="2" name="Warning" issues="39"/><Category id="3" name="Error" issues="116"/><Category id="4" name="Internal Error" issues="4"/><Category id="5" name="Fatal Error" issues="0"/></Categories><Issues><Issue id="10" category="3" count="19"/><Issue id="1016" category="3" count="1"/><Issue id="1049" category="3" count="3"/><Issue id="1062" category="3" count="36"/><Issue id="1113" category="3" count="1"/><Issue id="1220" category="4" count="4"/><Issue id="151" category="3" count="1"/><Issue id="36" category="3" count="10"/><Issue id="39" category="3" count="10"/><Issue id="40" category="3" count="9"/><Issue id="537" category="2" count="38"/><Issue id="55" category="3" count="2"/><Issue id="686" category="2" count="1"/><Issue id="78" category="3" count="19"/><Issue id="830" category="1" count="22"/><Issue id="96" category="3" count="1"/><Issue id="974" category="0" count="1"/><Issue id="98" category="3" count="4"/></Issues></Result><Result Date="2018-01-19T15:30:17"><Categories issues="181"><Category id="0" name="Elective Note" issues="1"/><Category id="1" name="Information" issues="22"/><Category id="2" name="Warning" issues="38"/><Category id="3" name="Error" issues="116"/><Category id="4" name="Internal Error" issues="4"/><Category id="5" name="Fatal Error" issues="0"/></Categories><Issues><Issue id="10" category="3" count="19"/><Issue id="1016" category="3" count="1"/><Issue id="1049" category="3" count="3"/><Issue id="1062" category="3" count="36"/><Issue id="1113" category="3" count="1"/><Issue id="1220" category="4" count="4"/><Issue id="151" category="3" count="1"/><Issue id="36" category="3" count="10"/><Issue id="39" category="3" count="10"/><Issue id="40" category="3" count="9"/><Issue id="537" category="2" count="38"/><Issue id="55" category="3" count="2"/><Issue id="78" category="3" count="19"/><Issue id="830" category="1" count="22"/><Issue id="96" category="3" count="1"/><Issue id="974" category="0" count="1"/><Issue id="98" category="3" count="4"/></Issues></Result><Result Date="2018-01-19T15:38:19"><Categories issues="86"><Category id="0" name="Elective Note" issues="25"/><Category id="1" name="Information" issues="20"/><Category id="2" name="Warning" issues="39"/><Category id="3" name="Error" issues="2"/><Category id="4" name="Internal Error" issues="0"/><Category id="5" name="Fatal Error" issues="0"/></Categories><Issues><Issue id="10" category="3" count="1"/><Issue id="1904" category="0" count="16"/><Issue id="1960" category="0" count="6"/><Issue id="1963" category="0" count="2"/><Issue id="537" category="2" count="38"/><Issue id="686" category="2" count="1"/><Issue id="773" category="1" count="1"/><Issue id="783" category="1" count="19"/><Issue id="96" category="3" count="1"/><Issue id="974" category="0" count="1"/></Issues></Result><Result Date="2018-01-19T16:16:37"><Categories issues="71"><Category id="0" name="Elective Note" issues="18"/><Category id="1" name="Information" issues="11"/><Category id="2" name="Warning" issues="39"/><Category id="3" name="Error" issues="3"/><Category id="4" name="Internal Error" issues="0"/><Category id="5" name="Fatal Error" issues="0"/></Categories><Issues><Issue id="10" category="3" count="2"/><Issue id="1904" category="0" count="16"/><Issue id="1960" category="0" count="1"/><Issue id="537" category="2" count="38"/><Issue id="686" category="2" count="1"/><Issue id="783" category="1" count="11"/><Issue id="96" category="3" count="1"/><Issue id="974" category="0" count="1"/></Issues></Result><Result Date="2018-01-19T16:33:18"><Categories issues="61"><Category id="0" name="Elective Note" issues="18"/><Category id="1" name="Information" issues="1"/><Category id="2" name="Warning" issues="39"/><Category id="3" name="Error" issues="3"/><Category id="4" name="Internal Error" issues="0"/><Category id="5" name="Fatal Error" issues="0"/></Categories><Issues><Issue id="10" category="3" count="2"/><Issue id="1904" category="0" count="16"/><Issue id="1960" category="0" count="1"/><Issue id="537" category="2" count="38"/><Issue id="686" category="2" count="1"/><Issue id="783" category="1" count="1"/><Issue id="96" category="3" count="1"/><Issue id="974" category="0" count="1"/></Issues></Result><Result Date="2018-01-19T16:50:40"><Categories issues="60"><Category id="0" name="Elective Note" issues="18"/><Category id="1" name="Information" issues="1"/><Category id="2" name="Warning" issues="39"/><Category id="3" name="Error" issues="2"/><Category id="4" name="Internal Error" issues="0"/><Category id="5" name="Fatal Error" issues="0"/></Categories><Issues><Issue id="10" category="3" count="1"/><Issue id="1904" category="0" count="16"/><Issue id="1960" category="0" count="1"/><Issue id="537" category="2" count="38"/><Issue id="686" category="2" count="1"/><Issue id="783" category="1" count="1"/><Issue id="96" category="3" count="1"/><Issue id="974" category="0" count="1"/></Issues></Result><Result Date="2018-01-19T16:57:41"><Categories issues="59"><Category id="0" name="Elective Note" issues="18"/><Category id="1" name="Information" issues="0"/><Category id="2" name="Warning" issues="39"/><Category id="3" name="Error" issues="2"/><Category id="4" name="Internal Error" issues="0"/><Category id="5" name="Fatal Error" issues="0"/></Categories><Issues><Issue id="10" category="3" count="1"/><Issue id="1904" category="0" count="16"/><Issue id="1960" category="0" count="1"/><Issue id="537" category="2" count="38"/><Issue id="686" category="2" count="1"/><Issue id="96" category="3" count="1"/><Issue id="974" category="0" count="1"/></Issues></Result><Result Date="2018-01-19T17:12:01"><Categories issues="59"><Category id="0" name="Elective Note" issues="18"/><Category id="1" name="Information" issues="0"/><Category id="2" name="Warning" issues="39"/><Category id="3" name="Error" issues="2"/><Category id="4" name="Internal Error" issues="0"/><Category id="5" name="Fatal Error" issues="0"/></Categories><Issues><Issue id="10" category="3" count="1"/><Issue id="1904" category="0" count="16"/><Issue id="1960" category="0" count="1"/><Issue id="537" category="2" count="38"/><Issue id="686" category="2" count="1"/><Issue id="96" category="3" count="1"/><Issue id="974" category="0" count="1"/></Issues></Result><Result Date="2018-01-19T17:30:57"><Categories issues="43"><Category id="0" name="Elective Note" issues="2"/><Category id="1" name="Information" issues="0"/><Category id="2" name="Warning" issues="39"/><Category id="3" name="Error" issues="2"/><Category id="4" name="Internal Error" issues="0"/><Category id="5" name="Fatal Error" issues="0"/></Categories><Issues><Issue id="10" category="3" count="1"/><Issue id="1960" category="0" count="1"/><Issue id="537" category="2" count="38"/><Issue id="686" category="2" count="1"/><Issue id="96" category="3" count="1"/><Issue id="974" category="0" count="1"/></Issues></Result><Result Date="2018-01-20T17:44:16"><Categories issues="43"><Category id="0" name="Elective Note" issues="2"/><Category id="1" name="Information" issues="0"/><Category id="2" name="Warning" issues="39"/><Category id="3" name="Error" issues="2"/><Category id="4" name="Internal Error" issues="0"/><Category id="5" name="Fatal Error" issues="0"/></Categories><Issues><Issue id="10" category="3" count="1"/><Issue id="1960" category="0" count="1"/><Issue id="537" category="2" count="38"/><Issue id="686" category="2" count="1"/><Issue id="96" category="3" count="1"/><Issue id="974" category="0" count="1"/></Issues></Result><Result Date="2018-01-20T18:00:14"><Categories issues="43"><Category id="0" name="Elective Note" issues="2"/><Category id="1" name="Information" issues="0"/><Category id="2" name="Warning" issues="39"/><Category id="3" name="Error" issues="2"/><Category id="4" name="Internal Error" issues="0"/><Category id="5" name="Fatal Error" issues="0"/></Categories><Issues><Issue id="10" category="3" count="1"/><Issue id="1960" category="0" count="1"/><Issue id="537" category="2" count="38"/><Issue id="686" category="2" count="1"/><Issue id="96" category="3" count="1"/><Issue id="974" category="0" count="1"/></Issues></Result><Result Date="2018-01-20T18:05:05"><Categories issues="43"><Category id="0" name="Elective Note" issues="2"/><Category id="1" name="Information" issues="0"/><Category id="2" name="Warning" issues="39"/><Category id="3" name="Error" issues="2"/><Category id="4" name="Internal Error" issues="0"/><Category id="5" name="Fatal Error" issues="0"/></Categories><Issues><Issue id="10" category="3" count="1"/><Issue id="1960" category="0" count="1"/><Issue id="537" category="2" count="38"/><Issue id="686" category="2" count="1"/><Issue id="96" category="3" count="1"/><Issue id="974" category="0" count="1"/></Issues></Result><Result Date="2018-01-20T18:05:49"><Categories issues="43"><Category id="0" name="Elective Note" issues="2"/><Category id="1" name="Information" issues="0"/><Category id="2" name="Warning" issues="39"/><Category id="3" name="Error" issues="2"/><Category id="4" name="Internal Error" issues="0"/><Category id="5" name="Fatal Error" issues="0"/></Categories><Issues><Issue id="10" category="3" count="1"/><Issue id="1960" category="0" count="1"/><Issue id="537" category="2" count="38"/><Issue id="686" category="2" count="1"/><Issue id="96" category="3" count="1"/><Issue id="974" category="0" count="1"/></Issues></Result><Result Date="2018-02-03T14:27:16"><Categories issues="43"><Category id="0" name="Elective Note" issues="2"/><Category id="1" name="Information" issues="0"/><Category id="2" name="Warning" issues="39"/><Category id="3" name="Error" issues="2"/><Category id="4" name="Internal Error" issues="0"/><Category id="5" name="Fatal Error" issues="0"/></Categories><Issues><Issue id="10" category="3" count="1"/><Issue id="1960" category="0" count="1"/><Issue id="537" category="2" count="38"/><Issue id="686" category="2" count="1"/><Issue id="96" category="3" count="1"/><Issue id="974" category="0" count="1"/></Issues></Result><Result Date="2018-02-03T15:36:16"><Categories issues="47"><Category id="0" name="Elective Note" issues="6"/><Category id="1" name="Information" issues="0"/><Category id="2" name="Warning" issues="39"/><Category id="3" name="Error" issues="2"/><Category id="4" name="Internal Error" issues="0"/><Category id="5" name="Fatal Error" issues="0"/></Categories><Issues><Issue id="10" category="3" count="1"/><Issue id="1960" category="0" count="3"/><Issue id="1963" category="0" count="2"/><Issue id="537" category="2" count="38"/><Issue id="686" category="2" count="1"/><Issue id="96" category="3" count="1"/><Issue id="974" category="0" count="1"/></Issues></Result><Result Date="2018-02-03T15:46:21"><Categories issues="45"><Category id="0" name="Elective Note" issues="4"/><Category id="1" name="Information" issues="0"/><Category id="2" name="Warning" issues="39"/><Category id="3" name="Error" issues="2"/><Category id="4" name="Internal Error" issues="0"/><Category id="5" name="Fatal Error" issues="0"/></Categories><Issues><Issue id="10" category="3" count="1"/><Issue id="1960" category="0" count="2"/><Issue id="1963" category="0" count="1"/><Issue id="537" category="2" count="38"/><Issue id="686" category="2" count="1"/><Issue id="96" category="3" count="1"/><Issue id="974" category="0" count="1"/></Issues></Result><Result Date="2018-02-03T15:50:23"><Categories issues="43"><Category id="0" name="Elective Note" issues="2"/><Category id="1" name="Information" issues="0"/><Category id="2" name="Warning" issues="39"/><Category id="3" name="Error" issues="2"/><Category id="4" name="Internal Error" issues="0"/><Category id="5" name="Fatal Error" issues="0"/></Categories><Issues><Issue id="10" category="3" count="1"/><Issue id="1960" category="0" count="1"/><Issue id="537" category="2" count="38"/><Issue id="686" category="2" count="1"/><Issue id="96" category="3" count="1"/><Issue id="974" category="0" count="1"/></Issues></Result><Result Date="2018-02-03T16:13:25"><Categories issues="5"><Category id="0" name="Elective Note" issues="2"/><Category id="1" name="Information" issues="0"/><Category id="2" name="Warning" issues="1"/><Category id="3" name="Error" issues="2"/><Category id="4" name="Internal Error" issues="0"/><Category id="5" name="Fatal Error" issues="0"/></Categories><Issues><Issue id="10" category="3" count="1"/><Issue id="1960" category="0" count="1"/><Issue id="686" category="2" count="1"/><Issue id="96" category="3" count="1"/><Issue id="974" category="0" count="1"/></Issues></Result><Result Date="2018-02-03T16:24:21"><Categories issues="43"><Category id="0" name="Elective Note" issues="2"/><Category id="1" name="Information" issues="0"/><Category id="2" name="Warning" issues="39"/><Category id="3" name="Error" issues="2"/><Category id="4" name="Internal Error" issues="0"/><Category id="5" name="Fatal Error" issues="0"/></Categories><Issues><Issue id="10" category="3" count="1"/><Issue id="1960" category="0" count="1"/><Issue id="537" category="2" count="38"/><Issue id="686" category="2" count="1"/><Issue id="96" category="3" count="1"/><Issue id="974" category="0" count="1"/></Issues></Result><Result Date="2018-02-03T16:25:12"><Categories issues="42"><Category id="0" name="Elective Note" issues="2"/><Category id="1" name="Information" issues="0"/><Category id="2" name="Warning" issues="39"/><Category id="3" name="Error" issues="1"/><Category id="4" name="Internal Error" issues="0"/><Category id="5" name="Fatal Error" issues="0"/></Categories><Issues><Issue id="1960" category="0" count="1"/><Issue id="537" category="2" count="38"/><Issue id="686" category="2" count="1"/><Issue id="96" category="3" count="1"/><Issue id="974" category="0" count="1"/></Issues></Result><Result Date="2018-02-03T16:26:06"><Categories issues="42"><Category id="0" name="Elective Note" issues="2"/><Category id="1" name="Information" issues="0"/><Category id="2" name="Warning" issues="39"/><Category id="3" name="Error" issues="1"/><Category id="4" name="Internal Error" issues="0"/><Category id="5" name="Fatal Error" issues="0"/></Categories><Issues><Issue id="1960" category="0" count="1"/><Issue id="537" category="2" count="38"/><Issue id="686" category="2" count="1"/><Issue id="96" category="3" count="1"/><Issue id="974" category="0" count="1"/></Issues></Result><Result Date="2018-02-03T16:32:56"><Categories issues="42"><Category id="0" name="Elective Note" issues="2"/><Category id="1" name="Information" issues="0"/><Category id="2" name="Warning" issues="39"/><Category id="3" name="Error" issues="1"/><Category id="4" name="Internal Error" issues="0"/><Category id="5" name="Fatal Error" issues="0"/></Categories><Issues><Issue id="1960" category="0" count="1"/><Issue id="537" category="2" count="38"/><Issue id="686" category="2" count="1"/><Issue id="96" category="3" count="1"/><Issue id="974" category="0" count="1"/></Issues></Result><Result Date="2018-02-03T16:36:41"><Categories issues="3"><Category id="0" name="Elective Note" issues="2"/><Category id="1" name="Information" issues="0"/><Category id="2" name="Warning" issues="1"/><Category id="3" name="Error" issues="0"/><Category id="4" name="Internal Error" issues="0"/><Category id="5" name="Fatal Error" issues="0"/></Categories><Issues><Issue id="1960" category="0" count="1"/><Issue id="686" category="2" count="1"/><Issue id="974" category="0" count="1"/></Issues></Result><Result Date="2018-02-03T16:44:04"><Categories issues="142"><Category id="0" name="Elective Note" issues="2"/><Category id="1" name="Information" issues="22"/><Category id="2" name="Warning" issues="0"/><Category id="3" name="Error" issues="114"/><Category id="4" name="Internal Error" issues="4"/><Category id="5" name="Fatal Error" issues="0"/></Categories><Issues><Issue id="10" category="3" count="18"/><Issue id="1016" category="3" count="1"/><Issue id="1049" category="3" count="3"/><Issue id="1062" category="3" count="36"/><Issue id="1113" category="3" count="1"/><Issue id="1220" category="4" count="4"/><Issue id="151" category="3" count="1"/><Issue id="1960" category="0" count="1"/><Issue id="36" category="3" count="10"/><Issue id="39" category="3" count="10"/><Issue id="40" category="3" count="9"/><Issue id="55" category="3" count="2"/><Issue id="78" category="3" count="19"/><Issue id="830" category="1" count="22"/><Issue id="974" category="0" count="1"/><Issue id="98" category="3" count="4"/></Issues></Result><Result Date="2018-02-03T16:46:36"><Categories issues="142"><Category id="0" name="Elective Note" issues="2"/><Category id="1" name="Information" issues="22"/><Category id="2" name="Warning" issues="0"/><Category id="3" name="Error" issues="114"/><Category id="4" name="Internal Error" issues="4"/><Category id="5" name="Fatal Error" issues="0"/></Categories><Issues><Issue id="10" category="3" count="18"/><Issue id="1016" category="3" count="1"/><Issue id="1049" category="3" count="3"/><Issue id="1062" category="3" count="36"/><Issue id="1113" category="3" count="1"/><Issue id="1220" category="4" count="4"/><Issue id="151" category="3" count="1"/><Issue id="1960" category="0" count="1"/><Issue id="36" category="3" count="10"/><Issue id="39" category="3" count="10"/><Issue id="40" category="3" count="9"/><Issue id="55" category="3" count="2"/><Issue id="78" category="3" count="19"/><Issue id="830" category="1" count="22"/><Issue id="974" category="0" count="1"/><Issue id="98" category="3" count="4"/></Issues></Result><Result Date="2018-02-03T16:47:33"><Categories issues="142"><Category id="0" name="Elective Note" issues="2"/><Category id="1" name="Information" issues="22"/><Category id="2" name="Warning" issues="0"/><Category id="3" name="Error" issues="114"/><Category id="4" name="Internal Error" issues="4"/><Category id="5" name="Fatal Error" issues="0"/></Categories><Issues><Issue id="10" category="3" count="18"/><Issue id="1016" category="3" count="1"/><Issue id="1049" category="3" count="3"/><Issue id="1062" category="3" count="36"/><Issue id="1113" category="3" count="1"/><Issue id="1220" category="4" count="4"/><Issue id="151" category="3" count="1"/><Issue id="1960" category="0" count="1"/><Issue id="36" category="3" count="10"/><Issue id="39" category="3" count="10"/><Issue id="40" category="3" count="9"/><Issue id="55" category="3" count="2"/><Issue id="78" category="3" count="19"/><Issue id="830" category="1" count="22"/><Issue id="974" category="0" count="1"/><Issue id="98" category="3" count="4"/></Issues></Result><Result Date="2018-02-03T16:51:48"><Categories issues="7"><Category id="0" name="Elective Note" issues="2"/><Category id="1" name="Information" issues="0"/><Category id="2" name="Warning" issues="1"/><Category id="3" name="Error" issues="0"/><Category id="4" name="Internal Error" issues="4"/><Category id="5" name="Fatal Error" issues="0"/></Categories><Issues><Issue id="1220" category="4" count="4"/><Issue id="1960" category="0" count="1"/><Issue id="686" category="2" count="1"/><Issue id="974" category="0" count="1"/></Issues></Result><Result Date="2018-02-03T16:52:46"><Categories issues="7"><Category id="0" name="Elective Note" issues="2"/><Category id="1" name="Information" issues="0"/><Category id="2" name="Warning" issues="1"/><Category id="3" name="Error" issues="0"/><Category id="4" name="Internal Error" issues="4"/><Category id="5" name="Fatal Error" issues="0"/></Categories><Issues><Issue id="1220" category="4" count="4"/><Issue id="1960" category="0" count="1"/><Issue id="686" category="2" count="1"/><Issue id="974" category="0" count="1"/></Issues></Result><Result Date="2018-02-03T16:53:36"><Categories issues="7"><Category id="0" name="Elective Note" issues="2"/><Category id="1" name="Information" issues="0"/><Category id="2" name="Warning" issues="1"/><Category id="3" name="Error" issues="0"/><Category id="4" name="Internal Error" issues="4"/><Category id="5" name="Fatal Error" issues="0"/></Categories><Issues><Issue id="1220" category="4" count="4"/><Issue id="1960" category="0" count="1"/><Issue id="686" category="2" count="1"/><Issue id="974" category="0" count="1"/></Issues></Result><Result Date="2018-02-03T16:55:58"><Categories issues="143"><Category id="0" name="Elective Note" issues="2"/><Category id="1" name="Information" issues="22"/><Category id="2" name="Warning" issues="1"/><Category id="3" name="Error" issues="114"/><Category id="4" name="Internal Error" issues="4"/><Category id="5" name="Fatal Error" issues="0"/></Categories><Issues><Issue id="10" category="3" count="18"/><Issue id="1016" category="3" count="1"/><Issue id="1049" category="3" count="3"/><Issue id="1062" category="3" count="36"/><Issue id="1113" category="3" count="1"/><Issue id="1220" category="4" count="4"/><Issue id="151" category="3" count="1"/><Issue id="1960" category="0" count="1"/><Issue id="36" category="3" count="10"/><Issue id="39" category="3" count="10"/><Issue id="40" category="3" count="9"/><Issue id="55" category="3" count="2"/><Issue id="686" category="2" count="1"/><Issue id="78" category="3" count="19"/><Issue id="830" category="1" count="22"/><Issue id="974" category="0" count="1"/><Issue id="98" category="3" count="4"/></Issues></Result><Result Date="2018-02-03T16:56:56"><Categories issues="143"><Category id="0" name="Elective Note" issues="2"/><Category id="1" name="Information" issues="22"/><Category id="2" name="Warning" issues="1"/><Category id="3" name="Error" issues="114"/><Category id="4" name="Internal Error" issues="4"/><Category id="5" name="Fatal Error" issues="0"/></Categories><Issues><Issue id="10" category="3" count="18"/><Issue id="1016" category="3" count="1"/><Issue id="1049" category="3" count="3"/><Issue id="1062" category="3" count="36"/><Issue id="1113" category="3" count="1"/><Issue id="1220" category="4" count="4"/><Issue id="151" category="3" count="1"/><Issue id="1960" category="0" count="1"/><Issue id="36" category="3" count="10"/><Issue id="39" category="3" count="10"/><Issue id="40" category="3" count="9"/><Issue id="55" category="3" count="2"/><Issue id="686" category="2" count="1"/><Issue id="78" category="3" count="19"/><Issue id="830" category="1" count="22"/><Issue id="974" category="0" count="1"/><Issue id="98" category="3" count="4"/></Issues></Result><Result Date="2018-02-03T16:58:47"><Categories issues="143"><Category id="0" name="Elective Note" issues="2"/><Category id="1" name="Information" issues="22"/><Category id="2" name="Warning" issues="0"/><Category id="3" name="Error" issues="115"/><Category id="4" name="Internal Error" issues="4"/><Category id="5" name="Fatal Error" issues="0"/></Categories><Issues><Issue id="10" category="3" count="18"/><Issue id="1016" category="3" count="1"/><Issue id="1049" category="3" count="3"/><Issue id="1062" category="3" count="36"/><Issue id="1113" category="3" count="1"/><Issue id="1220" category="4" count="4"/><Issue id="151" category="3" count="1"/><Issue id="1960" category="0" count="1"/><Issue id="36" category="3" count="10"/><Issue id="39" category="3" count="10"/><Issue id="40" category="3" count="9"/><Issue id="55" category="3" count="2"/><Issue id="72" category="3" count="1"/><Issue id="78" category="3" count="19"/><Issue id="830" category="1" count="22"/><Issue id="974" category="0" count="1"/><Issue id="98" category="3" count="4"/></Issues></Result><Result Date="2018-02-03T16:59:40"><Categories issues="3"><Category id="0" name="Elective Note" issues="2"/><Category id="1" name="Information" issues="0"/><Category id="2" name="Warning" issues="1"/><Category id="3" name="Error" issues="0"/><Category id="4" name="Internal Error" issues="0"/><Category id="5" name="Fatal Error" issues="0"/></Categories><Issues><Issue id="1960" category="0" count="1"/><Issue id="686" category="2" count="1"/><Issue id="974" category="0" count="1"/></Issues></Result><Result Date="2018-02-03T17:03:35"><Categories issues="3"><Category id="0" name="Elective Note" issues="2"/><Category id="1" name="Information" issues="0"/><Category id="2" name="Warning" issues="1"/><Category id="3" name="Error" issues="0"/><Category id="4" name="Internal Error" issues="0"/><Category id="5" name="Fatal Error" issues="0"/></Categories><Issues><Issue id="1960" category="0" count="1"/><Issue id="686" category="2" count="1"/><Issue id="974" category="0" count="1"/></Issues></Result><Result Date="2018-02-03T17:05:08"><Categories issues="143"><Category id="0" name="Elective Note" issues="2"/><Category id="1" name="Information" issues="22"/><Category id="2" name="Warning" issues="1"/><Category id="3" name="Error" issues="114"/><Category id="4" name="Internal Error" issues="4"/><Category id="5" name="Fatal Error" issues="0"/></Categories><Issues><Issue id="10" category="3" count="18"/><Issue id="1016" category="3" count="1"/><Issue id="1049" category="3" count="3"/><Issue id="1062" category="3" count="36"/><Issue id="1113" category="3" count="1"/><Issue id="1220" category="4" count="4"/><Issue id="151" category="3" count="1"/><Issue id="1960" category="0" count="1"/><Issue id="36" category="3" count="10"/><Issue id="39" category="3" count="10"/><Issue id="40" category="3" count="9"/><Issue id="55" category="3" count="2"/><Issue id="686" category="2" count="1"/><Issue id="78" category="3" count="19"/><Issue id="830" category="1" count="22"/><Issue id="974" category="0" count="1"/><Issue id="98" category="3" count="4"/></Issues></Result><Result Date="2018-02-03T17:08:30"><Categories issues="4"><Category id="0" name="Elective Note" issues="2"/><Category id="1" name="Information" issues="0"/><Category id="2" name="Warning" issues="2"/><Category id="3" name="Error" issues="0"/><Category id="4" name="Internal Error" issues="0"/><Category id="5" name="Fatal Error" issues="0"/></Categories><Issues><Issue id="1960" category="0" count="1"/><Issue id="686" category="2" count="2"/><Issue id="974" category="0" count="1"/></Issues></Result><Result Date="2018-02-03T17:08:55"><Categories issues="3"><Category id="0" name="Elective Note" issues="2"/><Category id="1" name="Information" issues="0"/><Category id="2" name="Warning" issues="1"/><Category id="3" name="Error" issues="0"/><Category id="4" name="Internal Error" issues="0"/><Category id="5" name="Fatal Error" issues="0"/></Categories><Issues><Issue id="1960" category="0" count="1"/><Issue id="686" category="2" count="1"/><Issue id="974" category="0" count="1"/></Issues></Result><Result Date="2018-02-03T17:13:48"><Categories issues="3"><Category id="0" name="Elective Note" issues="2"/><Category id="1" name="Information" issues="0"/><Category id="2" name="Warning" issues="1"/><Category id="3" name="Error" issues="0"/><Category id="4" name="Internal Error" issues="0"/><Category id="5" name="Fatal Error" issues="0"/></Categories><Issues><Issue id="1960" category="0" count="1"/><Issue id="686" category="2" count="1"/><Issue id="974" category="0" count="1"/></Issues></Result><Result Date="2018-02-03T17:14:55"><Categories issues="3"><Category id="0" name="Elective Note" issues="2"/><Category id="1" name="Information" issues="0"/><Category id="2" name="Warning" issues="1"/><Category id="3" name="Error" issues="0"/><Category id="4" name="Internal Error" issues="0"/><Category id="5" name="Fatal Error" issues="0"/></Categories><Issues><Issue id="1960" category="0" count="1"/><Issue id="686" category="2" count="1"/><Issue id="974" category="0" count="1"/></Issues></Result><Result Date="2018-02-03T17:15:54"><Categories issues="3"><Category id="0" name="Elective Note" issues="2"/><Category id="1" name="Information" issues="0"/><Category id="2" name="Warning" issues="1"/><Category id="3" name="Error" issues="0"/><Category id="4" name="Internal Error" issues="0"/><Category id="5" name="Fatal Error" issues="0"/></Categories><Issues><Issue id="1960" category="0" count="1"/><Issue id="686" category="2" count="1"/><Issue id="974" category="0" count="1"/></Issues></Result><Result Date="2018-02-03T17:35:58"><Categories issues="3"><Category id="0" name="Elective Note" issues="2"/><Category id="1" name="Information" issues="0"/><Category id="2" name="Warning" issues="1"/><Category id="3" name="Error" issues="0"/><Category id="4" name="Internal Error" issues="0"/><Category id="5" name="Fatal Error" issues="0"/></Categories><Issues><Issue id="1960" category="0" count="1"/><Issue id="686" category="2" count="1"/><Issue id="974" category="0" count="1"/></Issues></Result><Result Date="2018-02-03T17:41:12"><Categories issues="2"><Category id="0" name="Elective Note" issues="1"/><Category id="1" name="Information" issues="0"/><Category id="2" name="Warning" issues="1"/><Category id="3" name="Error" issues="0"/><Category id="4" name="Internal Error" issues="0"/><Category id="5" name="Fatal Error" issues="0"/></Categories><Issues><Issue id="1960" category="0" count="1"/><Issue id="686" category="2" count="1"/></Issues></Result><Result Date="2018-02-03T17:50:32"><Categories issues="2"><Category id="0" name="Elective Note" issues="1"/><Category id="1" name="Information" issues="0"/><Category id="2" name="Warning" issues="1"/><Category id="3" name="Error" issues="0"/><Category id="4" name="Internal Error" issues="0"/><Category id="5" name="Fatal Error" issues="0"/></Categories><Issues><Issue id="1960" category="0" count="1"/><Issue id="686" category="2" count="1"/></Issues></Result><Result Date="2018-02-03T17:53:12"><Categories issues="2"><Category id="0" name="Elective Note" issues="1"/><Category id="1" name="Information" issues="0"/><Category id="2" name="Warning" issues="1"/><Category id="3" name="Error" issues="0"/><Category id="4" name="Internal Error" issues="0"/><Category id="5" name="Fatal Error" issues="0"/></Categories><Issues><Issue id="1960" category="0" count="1"/><Issue id="686" category="2" count="1"/></Issues></Result><Result Date="2018-02-03T17:54:23"><Categories issues="2"><Category id="0" name="Elective Note" issues="1"/><Category id="1" name="Information" issues="0"/><Category id="2" name="Warning" issues="1"/><Category id="3" name="Error" issues="0"/><Category id="4" name="Internal Error" issues="0"/><Category id="5" name="Fatal Error" issues="0"/></Categories><Issues><Issue id="1960" category="0" count="1"/><Issue id="686" category="2" count="1"/></Issues></Result><Result Date="2018-02-03T17:55:41"><Categories issues="2"><Category id="0" name="Elective Note" issues="1"/><Category id="1" name="Information" issues="0"/><Category id="2" name="Warning" issues="1"/><Category id="3" name="Error" issues="0"/><Category id="4" name="Internal Error" issues="0"/><Category id="5" name="Fatal Error" issues="0"/></Categories><Issues><Issue id="1960" category="0" count="1"/><Issue id="686" category="2" count="1"/></Issues></Result><Result Date="2018-02-03T17:56:42"><Categories issues="2"><Category id="0" name="Elective Note" issues="1"/><Category id="1" name="Information" issues="0"/><Category id="2" name="Warning" issues="1"/><Category id="3" name="Error" issues="0"/><Category id="4" name="Internal Error" issues="0"/><Category id="5" name="Fatal Error" issues="0"/></Categories><Issues><Issue id="1960" category="0" count="1"/><Issue id="686" category="2" count="1"/></Issues></Result><Result Date="2018-02-03T17:56:52"><Categories issues="2"><Category id="0" name="Elective Note" issues="1"/><Category id="1" name="Information" issues="0"/><Category id="2" name="Warning" issues="1"/><Category id="3" name="Error" issues="0"/><Category id="4" name="Internal Error" issues="0"/><Category id="5" name="Fatal Error" issues="0"/></Categories><Issues><Issue id="1960" category="0" count="1"/><Issue id="686" category="2" count="1"/></Issues></Result><Result Date="2018-02-03T17:58:36"><Categories issues="3"><Category id="0" name="Elective Note" issues="1"/><Category id="1" name="Information" issues="0"/><Category id="2" name="Warning" issues="1"/><Category id="3" name="Error" issues="1"/><Category id="4" name="Internal Error" issues="0"/><Category id="5" name="Fatal Error" issues="0"/></Categories><Issues><Issue id="1960" category="0" count="1"/><Issue id="686" category="2" count="1"/><Issue id="72" category="3" count="1"/></Issues></Result><Result Date="2018-02-03T18:00:01"><Categories issues="3"><Category id="0" name="Elective Note" issues="1"/><Category id="1" name="Information" issues="0"/><Category id="2" name="Warning" issues="1"/><Category id="3" name="Error" issues="1"/><Category id="4" name="Internal Error" issues="0"/><Category id="5" name="Fatal Error" issues="0"/></Categories><Issues><Issue id="1960" category="0" count="1"/><Issue id="686" category="2" count="1"/><Issue id="72" category="3" count="1"/></Issues></Result><Result Date="2018-02-03T18:07:37"><Categories issues="2"><Category id="0" name="Elective Note" issues="1"/><Category id="1" name="Information" issues="0"/><Category id="2" name="Warning" issues="1"/><Category id="3" name="Error" issues="0"/><Category id="4" name="Internal Error" issues="0"/><Category id="5" name="Fatal Error" issues="0"/></Categories><Issues><Issue id="1960" category="0" count="1"/><Issue id="686" category="2" count="1"/></Issues></Result><Result Date="2018-02-03T18:09:12"><Categories issues="43"><Category id="0" name="Elective Note" issues="2"/><Category id="1" name="Information" issues="0"/><Category id="2" name="Warning" issues="39"/><Category id="3" name="Error" issues="2"/><Category id="4" name="Internal Error" issues="0"/><Category id="5" name="Fatal Error" issues="0"/></Categories><Issues><Issue id="10" category="3" count="1"/><Issue id="1960" category="0" count="1"/><Issue id="537" category="2" count="38"/><Issue id="686" category="2" count="1"/><Issue id="96" category="3" count="1"/><Issue id="974" category="0" count="1"/></Issues></Result><Result Date="2018-02-03T18:10:59"><Categories issues="2"><Category id="0" name="Elective Note" issues="1"/><Category id="1" name="Information" issues="0"/><Category id="2" name="Warning" issues="1"/><Category id="3" name="Error" issues="0"/><Category id="4" name="Internal Error" issues="0"/><Category id="5" name="Fatal Error" issues="0"/></Categories><Issues><Issue id="1960" category="0" count="1"/><Issue id="686" category="2" count="1"/></Issues></Result><Result Date="2018-02-03T18:11:53"><Categories issues="43"><Category id="0" name="Elective Note" issues="2"/><Category id="1" name="Information" issues="0"/><Category id="2" name="Warning" issues="39"/><Category id="3" name="Error" issues="2"/><Category id="4" name="Internal Error" issues="0"/><Category id="5" name="Fatal Error" issues="0"/></Categories><Issues><Issue id="10" category="3" count="1"/><Issue id="1960" category="0" count="1"/><Issue id="537" category="2" count="38"/><Issue id="686" category="2" count="1"/><Issue id="96" category="3" count="1"/><Issue id="974" category="0" count="1"/></Issues></Result><Result Date="2018-02-03T18:12:56"><Categories issues="2"><Category id="0" name="Elective Note" issues="1"/><Category id="1" name="Information" issues="0"/><Category id="2" name="Warning" issues="1"/><Category id="3" name="Error" issues="0"/><Category id="4" name="Internal Error" issues="0"/><Category id="5" name="Fatal Error" issues="0"/></Categories><Issues><Issue id="1960" category="0" count="1"/><Issue id="686" category="2" count="1"/></Issues></Result><Result Date="2018-02-03T18:16:09"><Categories issues="2"><Category id="0" name="Elective Note" issues="1"/><Category id="1" name="Information" issues="0"/><Category id="2" name="Warning" issues="1"/><Category id="3" name="Error" issues="0"/><Category id="4" name="Internal Error" issues="0"/><Category id="5" name="Fatal Error" issues="0"/></Categories><Issues><Issue id="1960" category="0" count="1"/><Issue id="686" category="2" count="1"/></Issues></Result><Result Date="2018-02-03T18:16:57"><Categories issues="2"><Category id="0" name="Elective Note" issues="1"/><Category id="1" name="Information" issues="0"/><Category id="2" name="Warning" issues="1"/><Category id="3" name="Error" issues="0"/><Category id="4" name="Internal Error" issues="0"/><Category id="5" name="Fatal Error" issues="0"/></Categories><Issues><Issue id="1960" category="0" count="1"/><Issue id="686" category="2" count="1"/></Issues></Result><Result Date="2018-02-03T18:22:45"><Categories issues="3"><Category id="0" name="Elective Note" issues="1"/><Category id="1" name="Information" issues="0"/><Category id="2" name="Warning" issues="2"/><Category id="3" name="Error" issues="0"/><Category id="4" name="Internal Error" issues="0"/><Category id="5" name="Fatal Error" issues="0"/></Categories><Issues><Issue id="1960" category="0" count="1"/><Issue id="686" category="2" count="2"/></Issues></Result><Result Date="2018-02-03T18:23:37"><Categories issues="142"><Category id="0" name="Elective Note" issues="1"/><Category id="1" name="Information" issues="22"/><Category id="2" name="Warning" issues="1"/><Category id="3" name="Error" issues="114"/><Category id="4" name="Internal Error" issues="4"/><Category id="5" name="Fatal Error" issues="0"/></Categories><Issues><Issue id="10" category="3" count="18"/><Issue id="1016" category="3" count="1"/><Issue id="1049" category="3" count="3"/><Issue id="1062" category="3" count="36"/><Issue id="1113" category="3" count="1"/><Issue id="1220" category="4" count="4"/><Issue id="151" category="3" count="1"/><Issue id="1960" category="0" count="1"/><Issue id="36" category="3" count="10"/><Issue id="39" category="3" count="10"/><Issue id="40" category="3" count="9"/><Issue id="55" category="3" count="2"/><Issue id="686" category="2" count="1"/><Issue id="78" category="3" count="19"/><Issue id="830" category="1" count="22"/><Issue id="98" category="3" count="4"/></Issues></Result><Result Date="2018-02-03T18:25:38"><Categories issues="142"><Category id="0" name="Elective Note" issues="1"/><Category id="1" name="Information" issues="22"/><Category id="2" name="Warning" issues="0"/><Category id="3" name="Error" issues="115"/><Category id="4" name="Internal Error" issues="4"/><Category id="5" name="Fatal Error" issues="0"/></Categories><Issues><Issue id="10" category="3" count="18"/><Issue id="1016" category="3" count="1"/><Issue id="1049" category="3" count="3"/><Issue id="1062" category="3" count="36"/><Issue id="1113" category="3" count="1"/><Issue id="1220" category="4" count="4"/><Issue id="151" category="3" count="1"/><Issue id="1960" category="0" count="1"/><Issue id="36" category="3" count="10"/><Issue id="39" category="3" count="10"/><Issue id="40" category="3" count="9"/><Issue id="55" category="3" count="2"/><Issue id="72" category="3" count="1"/><Issue id="78" category="3" count="19"/><Issue id="830" category="1" count="22"/><Issue id="98" category="3" count="4"/></Issues></Result><Result Date="2018-02-03T18:26:28"><Categories issues="142"><Category id="0" name="Elective Note" issues="1"/><Category id="1" name="Information" issues="22"/><Category id="2" name="Warning" issues="0"/><Category id="3" name="Error" issues="115"/><Category id="4" name="Internal Error" issues="4"/><Category id="5" name="Fatal Error" issues="0"/></Categories><Issues><Issue id="10" category="3" count="18"/><Issue id="1016" category="3" count="1"/><Issue id="1049" category="3" count="3"/><Issue id="1062" category="3" count="36"/><Issue id="1113" category="3" count="1"/><Issue id="1220" category="4" count="4"/><Issue id="151" category="3" count="1"/><Issue id="1960" category="0" count="1"/><Issue id="36" category="3" count="10"/><Issue id="39" category="3" count="10"/><Issue id="40" category="3" count="9"/><Issue id="55" category="3" count="2"/><Issue id="72" category="3" count="1"/><Issue id="78" category="3" count="19"/><Issue id="830" category="1" count="22"/><Issue id="98" category="3" count="4"/></Issues></Result><Result Date="2018-02-03T18:27:38"><Categories issues="2"><Category id="0" name="Elective Note" issues="1"/><Category id="1" name="Information" issues="0"/><Category id="2" name="Warning" issues="1"/><Category id="3" name="Error" issues="0"/><Category id="4" name="Internal Error" issues="0"/><Category id="5" name="Fatal Error" issues="0"/></Categories><Issues><Issue id="1960" category="0" count="1"/><Issue id="686" category="2" count="1"/></Issues></Result><Result Date="2018-02-03T18:28:30"><Categories issues="3"><Category id="0" name="Elective Note" issues="1"/><Category id="1" name="Information" issues="0"/><Category id="2" name="Warning" issues="1"/><Category id="3" name="Error" issues="1"/><Category id="4" name="Internal Error" issues="0"/><Category id="5" name="Fatal Error" issues="0"/></Categories><Issues><Issue id="1960" category="0" count="1"/><Issue id="686" category="2" count="1"/><Issue id="90" category="3" count="1"/></Issues></Result><Result Date="2018-02-03T18:29:11"><Categories issues="2"><Category id="0" name="Elective Note" issues="1"/><Category id="1" name="Information" issues="0"/><Category id="2" name="Warning" issues="1"/><Category id="3" name="Error" issues="0"/><Category id="4" name="Internal Error" issues="0"/><Category id="5" name="Fatal Error" issues="0"/></Categories><Issues><Issue id="1960" category="0" count="1"/><Issue id="686" category="2" count="1"/></Issues></Result><Result Date="2018-02-03T18:29:53"><Categories issues="2"><Category id="0" name="Elective Note" issues="1"/><Category id="1" name="Information" issues="0"/><Category id="2" name="Warning" issues="1"/><Category id="3" name="Error" issues="0"/><Category id="4" name="Internal Error" issues="0"/><Category id="5" name="Fatal Error" issues="0"/></Categories><Issues><Issue id="1960" category="0" count="1"/><Issue id="686" category="2" count="1"/></Issues></Result><Result Date="2018-02-03T18:30:24"><Categories issues="2"><Category id="0" name="Elective Note" issues="1"/><Category id="1" name="Information" issues="0"/><Category id="2" name="Warning" issues="1"/><Category id="3" name="Error" issues="0"/><Category id="4" name="Internal Error" issues="0"/><Category id="5" name="Fatal Error" issues="0"/></Categories><Issues><Issue id="1960" category="0" count="1"/><Issue id="686" category="2" count="1"/></Issues></Result></Results></AnalysisHistory>
